LICENSE
README.md
setup.py
paretoflow/__init__.py
paretoflow/flow.py
paretoflow/flow_net.py
paretoflow/flow_utils.py
paretoflow/multiple_model_predictor.py
paretoflow/multiple_model_predictor_net.py
paretoflow/paretoflow.py
paretoflow/paretoflow_utils.py
paretoflow/predictor_utils.py
paretoflow/utils.py
paretoflow.egg-info/PKG-INFO
paretoflow.egg-info/SOURCES.txt
paretoflow.egg-info/dependency_links.txt
paretoflow.egg-info/requires.txt
paretoflow.egg-info/top_level.txt