Metadata-Version: 2.1
Name: paretoflow
Version: 0.1.3
Summary: Paretoflow is a Python package for offline multi-objective optimization using     Generative Flow Models with Multi Predictors Guidance to approximate the Pareto front.
Home-page: https://github.com/StevenYuan666/ParetoFlow
Author: Ye Yuan, Can Chen
Author-email: ye.yuan3@mail.mcgill.ca
License: MIT License
Keywords: optimization
Platform: any
Classifier: Development Status :: 1 - Planning
Classifier: Intended Audience :: Developers
Classifier: Intended Audience :: Science/Research
Classifier: Operating System :: OS Independent
Classifier: License :: OSI Approved :: MIT License
Classifier: Programming Language :: Python
Classifier: Programming Language :: Python :: 3
Classifier: Programming Language :: Python :: 3.7
Classifier: Programming Language :: Python :: 3.8
Classifier: Programming Language :: Python :: 3.9
Classifier: Programming Language :: Python :: 3.10
Classifier: Programming Language :: Python :: 3.11
Classifier: Programming Language :: Python :: 3.12
Classifier: Topic :: Scientific/Engineering
Classifier: Topic :: Scientific/Engineering :: Artificial Intelligence
Classifier: Topic :: Scientific/Engineering :: Mathematics
Requires-Python: >=3.9
License-File: LICENSE
Requires-Dist: pymoo>=0.6.0
Requires-Dist: numpy>=1.23.2
Requires-Dist: scipy>=1.10.1
Requires-Dist: torch>=2.0.1
Requires-Dist: tqdm>=4.66.5
